gnnrl/___real_pruning.py
gnnrl/__init__.py
gnnrl/fine_tune.py
gnnrl/network_pruning.py
gnnrl/parameter.py
gnnrl/search.py
gnnrl/data/__init__.py
gnnrl/data/pytorch_cifar100/__init__.py
gnnrl/data/pytorch_cifar100/dataset.py
gnnrl/data/pytorch_cifar100/test.py
gnnrl/data/pytorch_cifar100/models/__init__.py
gnnrl/data/pytorch_cifar100/models/attention.py
gnnrl/data/pytorch_cifar100/models/resnet.py
gnnrl/data/pytorch_cifar100/models/vgg.py
gnnrl/example/__init__.py
gnnrl/example/pruning_example.py
gnnrl/graph_env/__init__.py
gnnrl/graph_env/feedback_calculation.py
gnnrl/graph_env/flops_calculation.py
gnnrl/graph_env/graph_construction.py
gnnrl/graph_env/graph_environment.py
gnnrl/graph_env/network_pruning.py
gnnrl/graph_env/share_layers.py
gnnrl/lib/__init__.py
gnnrl/lib/RL/__init__.py
gnnrl/lib/RL/agent.py
gnnrl/lib/RL/memory.py
gnnrl/lib/RL/tmp/__init__.py
gnnrl/lib/logs/__init__.py
gnnrl/logs/__init__.py
gnnrl/models/__init__.py
gnnrl/models/graph_encoder.py
gnnrl/models/graph_encoder_mean_pool.py
gnnrl/models/graph_encoder_plain.py
gnnrl/models/multi_stage_gcn.py
gnnrl/networks/__init__.py
gnnrl/networks/mobilenet.py
gnnrl/networks/mobilenet_cifar100.py
gnnrl/networks/mobilenetv2.py
gnnrl/networks/resnet.py
gnnrl/networks/shufflenet.py
gnnrl/networks/shufflenetv2.py
gnnrl/networks/pretrained_models/__init__.py
gnnrl/networks/pretrained_models/mobilenet_imagenet.pth.tar
gnnrl/networks/pretrained_models/cifar10/__init__.py
gnnrl/networks/pretrained_models/cifar10/resnet110.th
gnnrl/networks/pretrained_models/cifar10/resnet1202.th
gnnrl/networks/pretrained_models/cifar10/resnet20.th
gnnrl/networks/pretrained_models/cifar10/resnet32.th
gnnrl/networks/pretrained_models/cifar10/resnet44.th
gnnrl/networks/pretrained_models/cifar10/resnet56.th
gnnrl/utils/__init__.py
gnnrl/utils/batchwise_graphs.py
gnnrl/utils/load_networks.py
gnnrl/utils/net_info.py
gnnrl/utils/split_dataset.py
gnnrl/utils/train_utils.py
gnnrl-1.0.9.dist-info/LICENSE
gnnrl-1.0.9.dist-info/METADATA
gnnrl-1.0.9.dist-info/WHEEL
gnnrl-1.0.9.dist-info/top_level.txt
gnnrl-1.0.9.dist-info/RECORD
