Metadata-Version: 2.1
Name: gnnrl
Version: 1.0.9
Summary: gnnrl pipeline
Home-page: https://github.com/yusx-swapp/GNN-RL-Model-Compression/tree/master
Author: Sixing Yu
Author-email: yusx@iastate.edu
License: UNKNOWN
Project-URL: Bug Tracker, https://github.com/anonymous429/GNN-RL-Model-Compression/issues
Platform: UNKNOWN
Classifier: Programming Language :: Python :: 3
Classifier: License :: OSI Approved :: MIT License
Classifier: Operating System :: OS Independent
Requires-Python: >=3.6
License-File: LICENSE
